listings_db_contracts/__init__.py
listings_db_contracts/schemas.py
listings_db_contracts-1.0.6.dist-info/METADATA
listings_db_contracts-1.0.6.dist-info/WHEEL
listings_db_contracts-1.0.6.dist-info/top_level.txt
listings_db_contracts-1.0.6.dist-info/RECORD
