Metadata-Version: 2.4
Name: listings-db-contracts
Version: 1.0.6
Summary: Data contracts for the Finder property listings application
Author: giacomokavanagh
Author-email: giacomokavanagh <giacomokavanagh@gmail.com>
Project-URL: Homepage, https://github.com/giacomokavanagh/listings-db-mcp
Project-URL: Bug Tracker, https://github.com/giacomokavanagh/listings-db-mcp/issues
Classifier: Development Status :: 4 - Beta
Classifier: Intended Audience :: Developers
Classifier: License :: OSI Approved :: MIT License
Classifier: Operating System :: OS Independent
Classifier: Programming Language :: Python :: 3
Classifier: Programming Language :: Python :: 3.12
Classifier: Programming Language :: Python :: 3.13
Classifier: Programming Language :: Python :: 3.14
Requires-Python: >=3.8
Requires-Dist: pydantic>=2.12
Dynamic: author
Dynamic: requires-python
